jhoauthrefresh/__init__.py
jhoauthrefresh/config.py
jhoauthrefresh-0.3.0.dist-info/LICENSE.md
jhoauthrefresh-0.3.0.dist-info/METADATA
jhoauthrefresh-0.3.0.dist-info/WHEEL
jhoauthrefresh-0.3.0.dist-info/top_level.txt
jhoauthrefresh-0.3.0.dist-info/RECORD
