Metadata-Version: 2.1
Name: jhoauthrefresh
Version: 0.3.0
Home-page: https://github.com/ktaletsk/jhoauth-refresh
Author: Tim Head
License-File: LICENSE.md
Requires-Dist: notebook
